m3project_creator
