Metadata-Version: 1.1
Name: m3project-creator
Version: 1.2.1
Summary: M3 CMake project generator
Home-page: https://github.com/ahoarau/m3-cmake-project-creator
Author: Antoine Hoarau
Author-email: hoarau.robotics@gmail.com
License: GPL
Platform: UNKNOWN
Requires: gtk
